minimon/__init__.py
minimon/builder.py
minimon/cli.py
minimon/core.py
minimon/logging_utils.py
minimon/minimon.css
minimon/plugins/__init__.py
minimon/plugins/df.py
minimon/plugins/dmesg.py
minimon/plugins/ps.py
minimon/py.typed
minimon/server.py
minimon/sites/__init__.py
minimon/sites/minimon.log
minimon/sites/mvm.py
minimon/sites/private_infra.py
minimon/static/__init__.py
minimon/templates/__init__.py
minimon/tools/netiomon.css
minimon/tools/netiomon.py
minimon-0.1.7.dist-info/METADATA
minimon-0.1.7.dist-info/WHEEL
minimon-0.1.7.dist-info/entry_points.txt
minimon-0.1.7.dist-info/RECORD
