Metadata-Version: 2.1
Name: minimon
Version: 0.1.7
Summary: minimon
Home-page: https://projects.om-office.de/frans/minimon.git
Author: Frans Fürst
Author-email: frans.fuerst@protonmail.com
Requires-Python: >=3.10,<4.0.0
Classifier: Programming Language :: Python :: 3
Classifier: Programming Language :: Python :: 3.10
Classifier: Programming Language :: Python :: 3.11
Classifier: Programming Language :: Python :: 3.12
Requires-Dist: apparat (>=0.0.10,<0.0.11)
Requires-Dist: asyncinotify (>=4.0,<5.0)
Requires-Dist: asyncssh (>=2.13,<3.0)
Requires-Dist: bcrypt (>=4.0.1,<5.0.0)
Requires-Dist: psutil (>=5.9,<6.0)
Requires-Dist: pydantic (>=2,<3)
Requires-Dist: scapy (>=2.5,<3.0)
Requires-Dist: textual (>=0,<1)
Project-URL: Repository, https://projects.om-office.de/frans/minimon.git
